hyperjson5-0.1.0.dist-info/METADATA
hyperjson5-0.1.0.dist-info/WHEEL
hyperjson5/__init__.py
hyperjson5/hyperjson5.cpython-311-x86_64-linux-gnu.so
hyperjson5-0.1.0.dist-info/RECORD
