Metadata-Version: 2.1
Name: hyperjson5
Version: 0.1.0
Summary: A hyper-fast Python module for reading/writing JSON5 data
Keywords: fast,json,python,json5
Home-Page: https://github.com/Hinogary/hyperjson5
Author: Matthias Endler <matthias-endler@gmx.net>, Martin Quarda <martin@quarda.cz>
Author-email: Matthias Endler <matthias-endler@gmx.net>, Martin Quarda <martin@quarda.cz>
License: Apache-2.0
Project-URL: Source Code, https://github.com/Hinogary/hyperjson5
